taskdj/__init__.py
taskdj/admin.py
taskdj/connect.py
taskdj/exceptions.py
taskdj/models.py
taskdj/views.py
taskdj/migrations/0001_initial.py
taskdj/migrations/0002_auto_20160713_1508.py
taskdj/migrations/0003_auto_20160719_1022.py
taskdj/migrations/0004_auto_20160719_1022.py
taskdj/migrations/0005_auto_20181210_0102.py
taskdj/migrations/__init__.py
test_utils/migrations/0001_initial.py
test_utils/migrations/0002_delete_testtag.py
test_utils/migrations/0003_auto_20181210_0102.py
test_utils/migrations/0004_auto_20181210_0103.py
test_utils/migrations/0005_auto_20181210_1830.py
test_utils/migrations/__init__.py
django_taskd-0.0.1a1.dist-info/LICENSE.md
django_taskd-0.0.1a1.dist-info/METADATA
django_taskd-0.0.1a1.dist-info/WHEEL
django_taskd-0.0.1a1.dist-info/top_level.txt
django_taskd-0.0.1a1.dist-info/RECORD
