Metadata-Version: 2.1
Name: django-taskd
Version: 0.0.1a1
Summary: A taskd implementation for the Django web framework. Enables django applications to easily integrate
Home-page: https://github.com/Colorless-Green-Ideas/django-taskd
Author: amelia sabine
Author-email: amelia.sabine@getpizza.cat
License: AGPLv3
Platform: UNKNOWN
Classifier: Framework :: Django
Classifier: License :: OSI Approved :: GNU Affero General Public License v3 or later (AGPLv3+)
Classifier: Programming Language :: Python :: 2.7
Classifier: Programming Language :: Python :: 3.6
Classifier: Programming Language :: Python :: 3.7
Requires-Dist: django
Requires-Dist: taskc
Requires-Dist: requests
